stt_utils/__init__.py
stt_utils/py.typed
stt_utils/splitter.py
stt_utils/transcription.py
stt_utils-0.1.1.dist-info/licenses/LICENSE
stt_utils-0.1.1.dist-info/WHEEL
stt_utils-0.1.1.dist-info/METADATA
stt_utils-0.1.1.dist-info/RECORD
