Metadata-Version: 2.4
Name: stt-utils
Version: 0.1.1
Summary: A utility library for working with speech-to-text transcriptions.
Keywords: stt,speech to text,whisper,alignment,utility,audio,timestamps,transcription,closed captions,subtitles
Author: Mikhail Pankin
Author-email: Mikhail Pankin <mishapankin@gmail.com>
License-Expression: MIT
License-File: LICENSE
Classifier: Development Status :: 4 - Beta
Classifier: Intended Audience :: Developers
Classifier: License :: OSI Approved :: MIT License
Classifier: Programming Language :: Python :: 3
Classifier: Programming Language :: Python :: 3.9
Classifier: Programming Language :: Python :: 3.10
Classifier: Programming Language :: Python :: 3.11
Classifier: Programming Language :: Python :: 3.12
Classifier: Programming Language :: Python :: 3.13
Classifier: Programming Language :: Python :: 3.14
Classifier: Programming Language :: Python :: 3.15
Classifier: Topic :: Multimedia :: Sound/Audio :: Analysis
Classifier: Topic :: Software Development :: Libraries :: Python Modules
Requires-Dist: pydantic>=2.10
Requires-Dist: pydub>=0.25.1 ; extra == 'audio'
Requires-Python: >=3.9
Project-URL: Documentation, https://github.com/mishapankin/stt-utils#readme
Project-URL: Homepage, https://github.com/mishapankin/stt-utils
Project-URL: Issues, https://github.com/mishapankin/stt-utils/issues
Project-URL: Repository, https://github.com/mishapankin/stt-utils
Provides-Extra: audio
